sefazetllib/Builder.py
sefazetllib/__init__.py
sefazetllib/config/CustomLogging.py
sefazetllib/config/__init__.py
sefazetllib/etl/ETL.py
sefazetllib/etl/__init__.py
sefazetllib/extract/Extract.py
sefazetllib/extract/ExtractLocal.py
sefazetllib/extract/ExtractS3.py
sefazetllib/extract/ExtractSQL.py
sefazetllib/extract/ExtractStorage.py
sefazetllib/extract/__init__.py
sefazetllib/factory/Factory.py
sefazetllib/factory/__init__.py
sefazetllib/factory/platform/DatabasePlatform.py
sefazetllib/factory/platform/Platform.py
sefazetllib/factory/platform/PlatformFactory.py
sefazetllib/factory/platform/__init__.py
sefazetllib/factory/platform/database/MySQL.py
sefazetllib/factory/platform/database/PostgreSQL.py
sefazetllib/factory/platform/database/Redshift.py
sefazetllib/factory/platform/database/__init__.py
sefazetllib/factory/platform/dataframe/Default.py
sefazetllib/factory/platform/dataframe/Pandas.py
sefazetllib/factory/platform/dataframe/Spark.py
sefazetllib/factory/platform/dataframe/__init__.py
sefazetllib/load/Load.py
sefazetllib/load/LoadDB.py
sefazetllib/load/LoadLocal.py
sefazetllib/load/LoadS3.py
sefazetllib/load/LoadSQL.py
sefazetllib/load/LoadStorage.py
sefazetllib/load/__init__.py
sefazetllib/transform/ColumnsToLowerCase.py
sefazetllib/transform/ConvertColumnsType.py
sefazetllib/transform/DataFrameFilterRangeTransform.py
sefazetllib/transform/MinMaxLineTransform.py
sefazetllib/transform/QuartileTransform.py
sefazetllib/transform/RemoveColumnsByPrefix.py
sefazetllib/transform/RoundColumns.py
sefazetllib/transform/Transform.py
sefazetllib/transform/__init__.py
sefazetllib/utils/__init__.py
sefazetllib/utils/key/DefaultKey.py
sefazetllib/utils/key/Key.py
sefazetllib/utils/key/SurrogateKey.py
sefazetllib/utils/key/__init__.py
sefazetllib/utils/partition/DatePartition.py
sefazetllib/utils/partition/IncrementalRangePartition.py
sefazetllib/utils/partition/Partition.py
sefazetllib/utils/partition/__init__.py
sefazetllib/validate/DataValidate.py
sefazetllib-0.1.63.dist-info/LICENSE
sefazetllib-0.1.63.dist-info/METADATA
sefazetllib-0.1.63.dist-info/WHEEL
sefazetllib-0.1.63.dist-info/entry_points.txt
sefazetllib-0.1.63.dist-info/RECORD
