Metadata-Version: 2.1
Name: sefazetllib
Version: 0.1.63
Summary: sefazetllib is a library that provides a simplified and abstracted way to construct ETL/ELT pipelines.
Home-page: https://sa-east-1.console.aws.amazon.com/codesuite/codecommit/repositories/jobs-lib-sefaz-ce/browse?region=sa-east-1
License: Apache-2.0
Author: Felipe Gochi
Author-email: felipe.gochi@elogroup.com.br
Maintainer: Bruno Santos
Maintainer-email: bruno.santos@elogroup.com.br
Requires-Python: >=3.7.1,<4.0.0
Classifier: Intended Audience :: Developers
Classifier: License :: OSI Approved :: Apache Software License
Classifier: Operating System :: OS Independent
Classifier: Programming Language :: Python
Classifier: Programming Language :: Python :: 3
Classifier: Programming Language :: Python :: 3.8
Classifier: Programming Language :: Python :: 3.9
Classifier: Programming Language :: Python :: 3.10
Classifier: Programming Language :: Python :: 3.11
Classifier: Programming Language :: Python :: 3.12
Classifier: Programming Language :: Python :: 3.7
Classifier: Topic :: Software Development :: Libraries :: Python Modules
Requires-Dist: boto3 (>=1.24,<2.0)
Requires-Dist: click (>=8.1,<9.0)
Requires-Dist: pandas (>=2.0,<3.0)
Requires-Dist: pyarrow (>=6.0,<7.0)
Requires-Dist: pydeequ (>=1.4,<1.5)
Requires-Dist: python-dateutil (>=2.8,<3.0)
Requires-Dist: pyyaml (>=6.0,<7.0)
Project-URL: Documentation, https://main.unavailable.amplifyapp.com/
Project-URL: Repository, https://sa-east-1.console.aws.amazon.com/codesuite/codecommit/repositories/jobs-lib-sefaz-ce/browse?region=sa-east-1
